DesmosKiller/main.py
desmoskiller-9.0.dist-info/METADATA
desmoskiller-9.0.dist-info/WHEEL
desmoskiller-9.0.dist-info/top_level.txt
desmoskiller-9.0.dist-info/RECORD
