Metadata-Version: 2.4
Name: DesmosKiller
Version: 9.0
Author: YusufA442
Author-email: yusuf365820@gmail.com
License: Creative Commons Attribution-Noncommercial-Share Alike license
Requires-Dist: matplotlib
Dynamic: author
Dynamic: author-email
Dynamic: description
Dynamic: license
Dynamic: requires-dist
